pycomet/__init__.py
pycomet/ai.py
pycomet/cli.py
pycomet/config.py
pycomet/git.py
pycomet/models.py
pycomet/py.typed
pycomet_cli-0.1.2.dist-info/METADATA
pycomet_cli-0.1.2.dist-info/WHEEL
pycomet_cli-0.1.2.dist-info/entry_points.txt
pycomet_cli-0.1.2.dist-info/licenses/LICENSE
pycomet_cli-0.1.2.dist-info/RECORD
