Metadata-Version: 2.4
Name: pycomet-cli
Version: 0.1.2
Summary: AI-powered Git commit messages
Author-email: Jay W <git.jaydoubleu@gmail.com>
License: MIT
License-File: LICENSE
Requires-Python: >=3.8
Requires-Dist: click>=8.0.0
Requires-Dist: litellm==1.59.10
Requires-Dist: python-dotenv>=1.0.0
Requires-Dist: pyyaml>=6.0.0
Provides-Extra: dev
Requires-Dist: black>=24.0.0; extra == 'dev'
Requires-Dist: ruff>=0.3.0; extra == 'dev'
Provides-Extra: test
Requires-Dist: pytest-cov>=4.0.0; extra == 'test'
Requires-Dist: pytest>=7.0.0; extra == 'test'
Requires-Dist: python-dotenv>=1.0.0; extra == 'test'
Provides-Extra: tests
Requires-Dist: black>=23.0.0; extra == 'tests'
Requires-Dist: mypy>=1.0.0; extra == 'tests'
Requires-Dist: pytest>=7.4.0; extra == 'tests'
Requires-Dist: ruff>=0.1.0; extra == 'tests'
